firemelon
