Metadata-Version: 2.1
Name: firemelon
Version: 1.1.4
Summary: firemelon — Simple Password Generator
Home-page: https://github.com/evtn/firemelon
Author: evtn
Author-email: g@evtn.ru
License: MIT License
Download-URL: https://github.com/evtn/firemelon/archive/v1.1.4.tar.gz
Keywords: password
Platform: UNKNOWN
Classifier: Programming Language :: Python :: 3
Classifier: Programming Language :: Python :: 3.6
Classifier: Programming Language :: Python :: 3.7
Classifier: Programming Language :: Python :: 3.8
Classifier: Programming Language :: Python :: 3.9
Requires-Python: >=3.6.*
License-File: LICENSE
